{
  "sections": {
    "c72959ad-9620-4e94-ae33-1bde908e9701": {
      "type": "custom-code",
      "settings": {
        "custom_css": ":root {\n--spacing-sections-desktop: 120px;\n  --spacing-sections-tablet: 60px;\n  --spacing-sections-mobile: 48px;\n}\n.sf-home__collection-list .m-collection-card__link {\n  font-size: 24px;\n  line-height: 1.4;\n  font-weight: 400;\n}\n\n.sf-icon-box--large .m-icon-box__heading {\n  font-weight: 400;\n}\n.sf-icon-box--large .m-icon-box .m-button {\n  margin-top: 16px;\n}\n\n.m-richtext__subtitle,\n.m-lookbook__subheading {\n  font-weight: 500;\n}\n.sf-custom--collection-banner .container-full {\n  padding-left: 0;\n  padding-right: 0;\n}\n.sf-custom--collection-banner .m-image-card--button-fixed .m-button--fixed {\n  border-color: #e2e2e2;\n  padding-bottom: 20px;\n}\n.sf-custom--collection-banner .m-richtext__title {\n  line-height: 1.3;\n}\n\n.m-lookbook__header .m-lookbook__heading {\n  font-size: 29px;\n}\n@media (min-width: 768px) {\n  .sf-custom--collection-banner .m-image-card--button-fixed .m-button--fixed {\n    padding-bottom: 40px;\n    padding-top: 24px;\n  }\n  .sf-icon-box--large .m-icon-box__heading {\n    font-size: 32px;\n  }\n  .sf-icon-box--large .m-icon-box .m-button {\n    margin-top: 24px;\n  }\n}\n@media (min-width: 1024px) {\n  .m-footer--block-newsletter .m-footer--block-title {\n    font-size: 28px;\n    font-weight: 400;\n  }\n  .sf-custom--collection-banner .m-image-card__content {\n    padding-top: 70px;\n  }\n}\n@media (min-width: 1280px) {\n  .m-lookbook__header .m-lookbook__heading {\n    font-size: 42px;\n    line-height: 52px;\n  }\n  .sf-custom--collection-banner .m-richtext__subtitle,\n  .m-lookbook__header .m-lookbook__subheading {\n    font-size: 20px;\n    margin-bottom: 24px;\n  }\n}\n@media (min-width: 1536px) {\n  .sf-home__slideshow .m-slide__title {\n    font-size: 70px;\n    line-height: 80px;\n    margin-bottom: 40px;\n  }\n  .sf-custom--collection-banner .m-image-card__content {\n    padding-top: 110px;\n  }\n}\n\n@media (max-width: 767px) {\n  .sf-custom--collection-banner .m-image-card__content {\n    padding-bottom: 25px;\n    padding-top: 30px;\n  }\n  .sf-custom--collection-banner .m-image-card--button-fixed .m-button--fixed {\n    justify-content: center;\n    gap: 10px;\n    border: 0;\n    padding-bottom: 25px;\n  }\n  .sf-home__slideshow.m-slider--content-stack .m-slide__wrapper {\n    padding-top: 32px;\n  }\n  .sf-home__collection-list.m-collection-list .m-slider-controls,\n  .sf-home__collection-list .m-section__heading {\n    text-align: center;\n  }\n  body .m-lookbook__subheading {\n    margin-bottom: 12px;\n  }\n}"
      }
    },
    "1621243260e1af0c20": {
      "type": "slider",
      "blocks": {
        "1621243260e1af0c20-0": {
          "type": "slider_item",
          "settings": {
            "background": "",
            "mb_background": "",
            "content_in_container": false,
            "content_position": "left middle",
            "text_alignment": "left",
            "text_size": "large",
            "text_color": "black",
            "subheading": "New Arrivals",
            "title": "Venice Haute <br>\nCouture",
            "description": "",
            "image_link": "",
            "button_text": "Shop Now",
            "button_link": "",
            "button_style": "sf__btn-secondary",
            "button_size": "",
            "show_footer": true,
            "footer_alignment": "end",
            "footer_text": "The ReCotton Tee",
            "footer_button": "Shop Now",
            "footer_link": ""
          }
        },
        "1621243260e1af0c20-1": {
          "type": "slider_item",
          "settings": {
            "background": "",
            "mb_background": "",
            "content_in_container": false,
            "content_position": "left middle",
            "text_alignment": "left",
            "text_size": "large",
            "text_color": "black",
            "subheading": "New Arrivals",
            "title": "Responsible<br>\nDenim Lab",
            "description": "",
            "image_link": "",
            "button_text": "Shop Now",
            "button_link": "",
            "button_style": "sf__btn-secondary",
            "button_size": "",
            "show_footer": true,
            "footer_alignment": "end",
            "footer_text": "The ReCotton Tee",
            "footer_button": "Shop Now",
            "footer_link": ""
          }
        },
        "1621243260e1af0c20-2": {
          "type": "slider_item",
          "settings": {
            "background": "",
            "mb_background": "",
            "content_in_container": false,
            "content_position": "left middle",
            "text_alignment": "left",
            "text_size": "large",
            "text_color": "black",
            "subheading": "New Arrivals",
            "title": "Ultimate Winter<br>\nWarmer",
            "description": "",
            "image_link": "",
            "button_text": "Shop Now",
            "button_link": "",
            "button_style": "sf__btn-secondary",
            "button_size": "",
            "show_footer": true,
            "footer_alignment": "end",
            "footer_text": "The ReCotton Tee",
            "footer_button": "Shop Now",
            "footer_link": ""
          }
        }
      },
      "block_order": [
        "1621243260e1af0c20-0",
        "1621243260e1af0c20-1",
        "1621243260e1af0c20-2"
      ],
      "settings": {
        "container": "w-full",
        "slideshow_height": "adapt",
        "show_overlay": false,
        "dots_position": "right",
        "dots_color": "dark",
        "show_dots": true,
        "show_arrows": false,
        "autorotate": true,
        "autorotate_speed": 4,
        "use_content_above": false,
        "custom_class": "sf-home__slideshow",
        "animations": "inherit"
      }
    },
    "16225316461d1cff80": {
      "type": "collection-list",
      "blocks": {
        "65e38235-f03b-43c9-8590-38c9c656e51c": {
          "type": "collection_block",
          "settings": {
            "collection": "sandals",
            "title": "Sandals",
            "item_image": ""
          }
        },
        "694c01c9-a95f-4c09-9cf0-ec75f0131e98": {
          "type": "collection_block",
          "settings": {
            "collection": "glasses",
            "title": "Sunglasses",
            "item_image": ""
          }
        },
        "16225316461d1cff80-1": {
          "type": "collection_block",
          "settings": {
            "collection": "bags",
            "title": "Summer Bags",
            "item_image": ""
          }
        },
        "6d4abb37-5aa2-4499-a2b0-5d85f0d36eec": {
          "type": "collection_block",
          "settings": {
            "collection": "sneakers",
            "title": "Sneakers",
            "item_image": ""
          }
        },
        "12985deb-0775-45ce-80f6-6be7f3150a91": {
          "type": "collection_block",
          "settings": {
            "collection": "accessories",
            "title": "Accessories",
            "item_image": ""
          }
        },
        "16225316461d1cff80-2": {
          "type": "collection_block",
          "disabled": true,
          "settings": {
            "collection": "shoes",
            "title": "Shoes",
            "item_image": ""
          }
        },
        "07ebf095-1da2-4546-87f3-97e73a789e8d": {
          "type": "collection_block",
          "disabled": true,
          "settings": {
            "collection": "basic",
            "title": "Basic"
          }
        },
        "7a571158-7686-4e66-a693-4716fc905604": {
          "type": "collection_block",
          "disabled": true,
          "settings": {
            "collection": "tops",
            "title": "Tops"
          }
        }
      },
      "block_order": [
        "65e38235-f03b-43c9-8590-38c9c656e51c",
        "694c01c9-a95f-4c09-9cf0-ec75f0131e98",
        "16225316461d1cff80-1",
        "6d4abb37-5aa2-4499-a2b0-5d85f0d36eec",
        "12985deb-0775-45ce-80f6-6be7f3150a91",
        "16225316461d1cff80-2",
        "07ebf095-1da2-4546-87f3-97e73a789e8d",
        "7a571158-7686-4e66-a693-4716fc905604"
      ],
      "settings": {
        "heading": "Shop by Categories",
        "heading_size": "h3",
        "subheading": "",
        "description": "",
        "header_alignment": "left",
        "container": "container-fluid",
        "background_color": "",
        "layout": "grid",
        "expanded": true,
        "card_style": "inside",
        "text_alignment": "left",
        "hover_effect": "scaling-up",
        "show_product_count": true,
        "count_inline_title": true,
        "image_rounded": false,
        "items_per_row": 3,
        "item_gap": 40,
        "enable_slider": true,
        "show_pagination": true,
        "show_navigation": true,
        "autorotate": false,
        "autorotate_speed": 4,
        "mobile_disable_slider": false,
        "use_scroll_mobile": true,
        "mobile_gap": 16,
        "hidden_slide_control_mobile": false,
        "padding_top": 0,
        "padding_bottom": 0,
        "custom_class": "sf-home__collection-list",
        "animations": "inherit"
      }
    },
    "162251092958fcda7c": {
      "type": "product-tabs",
      "blocks": {
        "162251092958fcda7c-0": {
          "type": "tab",
          "settings": {
            "title": "best sellers",
            "collection": "fashion-2023"
          }
        },
        "162251092958fcda7c-1": {
          "type": "tab",
          "settings": {
            "title": "new arrivals",
            "collection": "fashion-2023-new-arrivals"
          }
        }
      },
      "block_order": [
        "162251092958fcda7c-0",
        "162251092958fcda7c-1"
      ],
      "settings": {
        "heading": "You are in",
        "heading_size": "h3",
        "subheading": "",
        "description": "",
        "header_alignment": "center",
        "container": "container-fluid",
        "background_color": "rgba(0,0,0,0)",
        "tab_header": "select",
        "limit": 10,
        "show_button": true,
        "button_type": "link",
        "button_label": "Shop All Products",
        "button_style": "m-button--secondary",
        "button_size": "",
        "pcard_layout": "",
        "pcard_image_ratio": "",
        "show_vendor": false,
        "items_per_row": 5,
        "item_gap": 30,
        "enable_slider": false,
        "show_navigation": false,
        "show_pagination": false,
        "mobile_disable_slider": false,
        "use_scroll_mobile": true,
        "item_gap_mobile": 16,
        "padding_top": 0,
        "padding_bottom": 0,
        "custom_class": "sf-home__product-tab",
        "animations": "inherit"
      }
    },
    "7ea56e8d-5794-4708-8812-8ee9604a3a21": {
      "type": "custom-content",
      "blocks": {
        "template--15977492021425__7ea56e8d-5794-4708-8812-8ee9604a3a21-1678440566c64de1a8-1": {
          "type": "image",
          "settings": {
            "image": "",
            "link": "",
            "width": "50%",
            "alignment": "center",
            "block_custom_class": "",
            "animations": "zoom-fade"
          }
        },
        "5c5877d5-05b2-4a50-81e3-78c3f6d0d833": {
          "type": "image_card",
          "settings": {
            "width": "50%",
            "content_position": "top_center",
            "content_alignment": "center",
            "text_size": "medium",
            "text_color": "black",
            "image": "",
            "link": "shopify:\/\/collections\/all",
            "title": "The ReLeather Beige<br> Tennis Shoe",
            "subtitle": "New collection",
            "button_label": "Shop New Collection",
            "button_style": "m-button--primary",
            "button_size": "m-button--large",
            "button_fixed": true,
            "use_content_above": true,
            "block_custom_class": "",
            "animations": "inherit"
          }
        }
      },
      "block_order": [
        "template--15977492021425__7ea56e8d-5794-4708-8812-8ee9604a3a21-1678440566c64de1a8-1",
        "5c5877d5-05b2-4a50-81e3-78c3f6d0d833"
      ],
      "custom_css": [

      ],
      "settings": {
        "heading": "",
        "heading_size": "h3",
        "subheading": "",
        "description": "",
        "header_alignment": "center",
        "container": "w-full",
        "background_color": "",
        "gap": 0,
        "use_scroll_mobile": false,
        "gap_mobile": 0,
        "padding_top": 0,
        "padding_bottom": 0,
        "custom_class": "sf-custom--collection-banner"
      }
    },
    "7731d6df-9d53-4c34-9efb-98fac2fa365d": {
      "type": "icon-box",
      "blocks": {
        "template--15977492021425__7731d6df-9d53-4c34-9efb-98fac2fa365d-16769649642102c2d8-1": {
          "type": "iconbox",
          "settings": {
            "image": "",
            "image_by_url": "",
            "title": "The Cashmere Cardigan",
            "description": "<p>Add a free personalized note during checkout.<\/p>",
            "link": "",
            "button_label": "Shop Cardigans",
            "button_link": "shopify:\/\/collections\/all",
            "button_style": "m-button--secondary",
            "button_size": ""
          }
        },
        "template--15977492021425__7731d6df-9d53-4c34-9efb-98fac2fa365d-16769649642102c2d8-0": {
          "type": "iconbox",
          "settings": {
            "image": "",
            "image_by_url": "",
            "title": "The Italian Chelsea Boot",
            "description": "<p>Brittany Bathgate shows how less is more.<\/p>",
            "link": "",
            "button_label": "Shop bags",
            "button_link": "shopify:\/\/collections\/all",
            "button_style": "m-button--secondary",
            "button_size": ""
          }
        },
        "template--15977492021425__7731d6df-9d53-4c34-9efb-98fac2fa365d-16769649642102c2d8-2": {
          "type": "iconbox",
          "settings": {
            "image": "",
            "image_by_url": "",
            "title": "Transit Fanny Pack",
            "description": "<p>Brittany Bathgate shows how less is more.<\/p>",
            "link": "",
            "button_label": "Shop Shirts",
            "button_link": "shopify:\/\/collections\/all",
            "button_style": "m-button--secondary",
            "button_size": ""
          }
        }
      },
      "block_order": [
        "template--15977492021425__7731d6df-9d53-4c34-9efb-98fac2fa365d-16769649642102c2d8-1",
        "template--15977492021425__7731d6df-9d53-4c34-9efb-98fac2fa365d-16769649642102c2d8-0",
        "template--15977492021425__7731d6df-9d53-4c34-9efb-98fac2fa365d-16769649642102c2d8-2"
      ],
      "custom_css": [
        ".sf__btn {margin-top: 24px; padding-left: 25px; padding-right: 25px; border-color: #dadada;}"
      ],
      "settings": {
        "heading": "Season Collection",
        "heading_size": "h3",
        "subheading": "",
        "description": "",
        "header_alignment": "center",
        "container": "container-fluid",
        "background_color": "rgba(0,0,0,0)",
        "item_per_row": 3,
        "item_gap": 30,
        "item_gap_mobile": 16,
        "card_style": "vertical",
        "image_max_width": "100%",
        "content_alignment": "start",
        "hover_effect": "scaling-up",
        "enable_slider": false,
        "show_pagination": false,
        "show_navigation": false,
        "use_scroll_mobile": true,
        "use_grid_column_mb": false,
        "padding_top": 0,
        "padding_bottom": 0,
        "custom_class": "sf-icon-box--large",
        "animations": "inherit"
      }
    },
    "721388d4-7859-4958-b320-c705800d31d9": {
      "type": "lookbook",
      "blocks": {
        "65a3de0e-b3e4-4c97-b3e5-2f2f03d92449": {
          "type": "lookbook-slider",
          "settings": {
            "sub_title": "Favorite products",
            "title": "Shop this look",
            "text": "",
            "content_alignment": "center",
            "text_color": "black",
            "background_color": "",
            "image": "",
            "button_style": "dark",
            "top_1": 32,
            "left_1": 44,
            "product_1": "seamless-crop-top",
            "top_2": 45,
            "left_2": 50,
            "product_2": "seamless-cycling-shorts",
            "top_3": 87,
            "left_3": 45,
            "product_3": "contrast-trainers-with-mesh-detail",
            "top_4": 0,
            "left_4": 0,
            "product_4": "",
            "top_5": 20,
            "left_5": 0,
            "product_5": "",
            "product_per_view": "2",
            "show_pagination": true,
            "show_navigation": true,
            "pcard_layout": "",
            "pcard_image_ratio": "",
            "show_vendor": false,
            "hide_title": false
          }
        }
      },
      "block_order": [
        "65a3de0e-b3e4-4c97-b3e5-2f2f03d92449"
      ],
      "settings": {
        "heading": "",
        "heading_size": "h3",
        "subheading": "",
        "description": "",
        "header_alignment": "center",
        "container": "container-fluid",
        "background_color": "rgba(0,0,0,0)",
        "image_aspect_ratio": "3\/4",
        "padding_top": 0,
        "padding_bottom": 0,
        "custom_class": "",
        "animations": "inherit"
      }
    },
    "de0a17f2-43a3-4a11-a2b7-f2092303f3a7": {
      "type": "custom-content",
      "blocks": {
        "9ef56b70-2b08-4f55-b9ef-5a1539ae0225": {
          "type": "handpicked_products",
          "settings": {
            "width": "50%",
            "alignment": "center",
            "subtitle": "Favorite products",
            "title": "Shop this look",
            "text": "",
            "button_label": "",
            "button_link": "",
            "button_style": "sf__btn-primary",
            "button_size": "",
            "text_size": "medium",
            "content_alignment": "center",
            "product_list": [
              "seamless-crop-top",
              "seamless-cycling-shorts",
              "cateye-sunglasses"
            ],
            "product_to_show": 6,
            "items_per_row": 2,
            "item_gap": 30,
            "pcard_layout": "",
            "pcard_image_ratio": "",
            "show_vendor": false,
            "hide_title": false,
            "enable_slider": true,
            "show_pagination": true,
            "show_navigation": true,
            "use_scroll_mobile": true,
            "item_gap_mobile": 16,
            "block_custom_class": "",
            "animations": "inherit"
          }
        },
        "9a3e8bcd-5794-42eb-8e4e-2a5865b48e29": {
          "type": "video",
          "disabled": true,
          "settings": {
            "video_type": "shopify",
            "shopify_video": "",
            "video_link": "",
            "ratio": "4:3",
            "video_title": "",
            "text_size": "medium",
            "text_color": "white",
            "play_style": "solid",
            "play_size": "medium",
            "autoplay": true,
            "loop": true,
            "muted": true,
            "show_controls": false,
            "width": "50%",
            "alignment": "start",
            "block_custom_class": "sf-video--custom-content",
            "animations": "inherit"
          }
        },
        "193adc84-8ce7-4336-b4c7-7142a2c81b10": {
          "type": "image",
          "settings": {
            "image": "",
            "link": "",
            "width": "50%",
            "alignment": "center",
            "block_custom_class": "",
            "animations": "inherit"
          }
        }
      },
      "block_order": [
        "9ef56b70-2b08-4f55-b9ef-5a1539ae0225",
        "9a3e8bcd-5794-42eb-8e4e-2a5865b48e29",
        "193adc84-8ce7-4336-b4c7-7142a2c81b10"
      ],
      "disabled": true,
      "settings": {
        "heading": "",
        "heading_size": "h3",
        "subheading": "",
        "description": "",
        "header_alignment": "center",
        "container": "container-fluid",
        "background_color": "",
        "gap": 0,
        "use_scroll_mobile": false,
        "gap_mobile": 16,
        "padding_top": 0,
        "padding_bottom": 0,
        "custom_class": "m-custom-content--favorite-products"
      }
    },
    "11cfb44f-b725-4daf-8ee7-4bbf2c63914d": {
      "type": "instagram",
      "settings": {
        "heading": "Follow us Instagram",
        "heading_size": "h3",
        "subheading": "",
        "description": "Tag <span class=\"text-black\">@minimog<\/span> in your Instagram photos for a chance to be featured here.<br>\nFind more inspiration on <a href=\"#\">our Instagram.<\/a>",
        "header_alignment": "center",
        "container": "container-fluid",
        "background_color": "rgba(0,0,0,0)",
        "layout": "grid",
        "images_count": 5,
        "grid_columns": 5,
        "gap": 30,
        "mobile_gap": 10,
        "profile": "https:\/\/www.instagram.com\/minimog.trendy\/",
        "button_label": "",
        "padding_top": 0,
        "padding_bottom": 0,
        "custom_class": ""
      }
    },
    "16225125199f82d8fe": {
      "type": "icon-box",
      "blocks": {
        "16225125199f82d8fe-0": {
          "type": "iconbox",
          "settings": {
            "image": "",
            "image_by_url": "",
            "title": "Free Shipping",
            "description": "<p>Free Shipping for orders over £130<\/p>",
            "link": "",
            "button_label": "",
            "button_link": "",
            "button_style": "sf__btn-link",
            "button_size": ""
          }
        },
        "16225125199f82d8fe-1": {
          "type": "iconbox",
          "settings": {
            "image": "",
            "image_by_url": "",
            "title": "Money Guarantee",
            "description": "<p>Within 30 days for an exchange.<\/p>",
            "link": "",
            "button_label": "",
            "button_link": "",
            "button_style": "sf__btn-link",
            "button_size": ""
          }
        },
        "16225125199f82d8fe-2": {
          "type": "iconbox",
          "settings": {
            "image": "",
            "image_by_url": "",
            "title": "Online Support",
            "description": "<p>24 hours a day, 7 days a week<\/p>",
            "link": "",
            "button_label": "",
            "button_link": "",
            "button_style": "sf__btn-link",
            "button_size": ""
          }
        },
        "71deafbb-3baf-443a-a087-3f7b8af7b9fa": {
          "type": "iconbox",
          "settings": {
            "image": "",
            "image_by_url": "",
            "title": "Flexible Payment",
            "description": "<p>Pay with Multiple Credit Cards<\/p>",
            "link": "",
            "button_label": "",
            "button_link": "",
            "button_style": "sf__btn-link",
            "button_size": ""
          }
        }
      },
      "block_order": [
        "16225125199f82d8fe-0",
        "16225125199f82d8fe-1",
        "16225125199f82d8fe-2",
        "71deafbb-3baf-443a-a087-3f7b8af7b9fa"
      ],
      "settings": {
        "heading": "",
        "heading_size": "h3",
        "subheading": "",
        "description": "",
        "header_alignment": "center",
        "container": "container-fluid",
        "background_color": "#ffffff",
        "item_per_row": 4,
        "item_gap": 30,
        "item_gap_mobile": 10,
        "card_style": "horizontal",
        "image_max_width": "60px",
        "content_alignment": "start",
        "hover_effect": "none",
        "enable_slider": false,
        "show_pagination": true,
        "show_navigation": true,
        "use_scroll_mobile": false,
        "use_grid_column_mb": false,
        "padding_top": 46,
        "padding_bottom": 46,
        "custom_class": "m-icon-box--small",
        "animations": "inherit"
      }
    }
  },
  "order": [
    "c72959ad-9620-4e94-ae33-1bde908e9701",
    "1621243260e1af0c20",
    "16225316461d1cff80",
    "162251092958fcda7c",
    "7ea56e8d-5794-4708-8812-8ee9604a3a21",
    "7731d6df-9d53-4c34-9efb-98fac2fa365d",
    "721388d4-7859-4958-b320-c705800d31d9",
    "de0a17f2-43a3-4a11-a2b7-f2092303f3a7",
    "11cfb44f-b725-4daf-8ee7-4bbf2c63914d",
    "16225125199f82d8fe"
  ]
}